<?xml version="1.0"?>
<!DOCTYPE hibernate-mapping PUBLIC "-//Hibernate/Hibernate Mapping DTD 3.0//EN"
"http://hibernate.sourceforge.net/hibernate-mapping-3.0.dtd">
<hibernate-mapping>
    <class name="nju.software.jxjs.model.TJxjs" table="T_JXJS" schema="dbo" catalog="JUDGE">
        <cache usage="read-write" />
        <id name="jxjsbh" type="int">
            <column name="JXJSBH" />
            <generator class="assigned" />
        </id>
        
        <property name="sxajxh" type="int">
            <column name="SXAJXH" />
        </property>
        <property name="laajxh" type="int">
            <column name="LAAJXH" />
        </property>
        
        <property name="sxah" type="string">
            <column name="SXAH" />
        </property>
        <property name="sxfybh" type="string">
            <column name="SXFYBH" />
        </property>
        
        <property name="sqsj" type="java.util.Date">
            <column name="SQSJ" />
        </property>
        <property name="sqcs" type="int">
            <column name="SQCS" />
        </property>
        
        <property name="ajztbh" type="string">
            <column name="AJZTBH" />
        </property>
        <property name="fxdd" type="string">
            <column name="FXDD" />
        </property>
        
        <property name="ypksrq" type="java.util.Date">
            <column name="YPKSRQ" />
        </property>
        <property name="ypjsrq" type="java.util.Date">
            <column name="YPJSRQ" />
        </property> 
        
        <property name="sqksrq" type="java.util.Date">
            <column name="SQKSRQ" />
        </property>
        <property name="sqjsrq" type="java.util.Date">
            <column name="SQJSRQ" />
        </property>             
        
        <property name="rjrq" type="java.util.Date">
            <column name="RJRQ" />
        </property>
        <property name="sfjs" type="int">
            <column name="SFJS" />
        </property>                                   
    </class>
</hibernate-mapping>
